pyspectrum/__init__.py
pyspectrum/data.py
pyspectrum/errors.py
pyspectrum/spectrometer.py
pyspectrum/usb_context.py
pyspectrum/usb_device.py
libspectrum-0.0.2.dist-info/METADATA
libspectrum-0.0.2.dist-info/WHEEL
libspectrum-0.0.2.dist-info/RECORD
