Metadata-Version: 2.3
Name: libspectrum
Version: 0.0.2
Summary: Library for communication with VMK spectrometer through USB interface
Project-URL: Documentation, https://routybor.github.io/libspectrum/
Project-URL: Source code, https://github.com/Routybor/libspectrum
Author-email: Egor Bondar <egorbondar825@gmail.com>
Maintainer-email: Egor Bondar <egorbondar825@gmail.com>
Keywords: USB,library,spectrometer
Requires-Python: >=3.11
Requires-Dist: ftd2xx==1.3.8; platform_system == 'Windows'
Requires-Dist: matplotlib
Requires-Dist: numpy
Requires-Dist: scipy
Provides-Extra: mkdocs
Requires-Dist: mkdocs; extra == 'mkdocs'
Requires-Dist: mkdocs-jupyter; extra == 'mkdocs'
Requires-Dist: mkdocs-material; extra == 'mkdocs'
Requires-Dist: mkdocstrings; extra == 'mkdocs'
Requires-Dist: mkdocstrings[python]; extra == 'mkdocs'
